danila/Danila_balka_classify.py
danila/Danila_detail_CNN.py
danila/Danila_detail_yolo_dop_yolo_dop_CNN.py
danila/__init__.py
danila/danila.py
danila/danila_balka.py
danila/danila_balka_base.py
danila/danila_balka_classify_params.py
danila/danila_balka_classify_prod.py
danila/danila_balka_params.py
danila/danila_balka_redone.py
danila/danila_balka_text_detect.py
danila/danila_balka_text_detect_base.py
danila/danila_balka_text_detect_params.py
danila/danila_balka_text_recognize.py
danila/danila_balka_text_recognize_base.py
danila/danila_balka_text_recognize_params.py
danila/danila_balka_text_recognize_redone.py
danila/danila_detail.py
danila/danila_detail_params.py
danila/danila_rama.py
danila/danila_rama_base.py
danila/danila_rama_classify.py
danila/danila_rama_classify_params.py
danila/danila_rama_classify_prod.py
danila/danila_rama_params.py
danila/danila_rama_redone.py
danila/danila_rama_text_detect.py
danila/danila_rama_text_detect_base.py
danila/danila_rama_text_detect_params.py
danila/danila_rama_text_recognize.py
danila/danila_rama_text_recognize_base.py
danila/danila_rama_text_recognize_number_shift_redetect.py
danila/danila_rama_text_recognize_number_shift_redetect_redone.py
danila/danila_rama_text_recognize_params.py
danila/danila_rama_text_recognize_redone.py
danila/danila_v1.py
danila/danila_v10.py
danila/danila_v11.py
danila/danila_v2.py
danila/danila_v3.py
danila/danila_v4.py
danila/danila_v5.py
danila/danila_v6.py
danila/danila_v7.py
danila/danila_v8.py
danila/danila_v9.py
danila/danila_vagon.py
danila/danila_vagon_params.py
danila/danila_vagon_text_detect.py
danila/danila_vagon_text_detect_base.py
danila/danila_vagon_text_detect_params.py
danila/danila_vagon_text_recognize.py
danila/danila_vagon_text_recognize_base.py
danila/danila_vagon_text_recognize_params.py
danila/danila_balka/__init__.py
danila/danila_balka/danila_balka.py
danila/danila_balka/danila_balka_base.py
danila/danila_balka/danila_balka_params.py
danila_lib-3.1.0.dist-info/METADATA
danila_lib-3.1.0.dist-info/WHEEL
danila_lib-3.1.0.dist-info/top_level.txt
danila_lib-3.1.0.dist-info/RECORD
