Metadata-Version: 2.1
Name: danila-lib
Version: 3.1.0
Summary: This is the module for detecting and classifying text on rama pictures
Home-page: https://github.com/Arseniy-Zhuck/danila_lib
Author: arseniy_zhuck
Author-email: arseniyzhuck@mail.ru
Project-URL: GitHub, https://github.com/Arseniy-Zhuck/danila_lib
Keywords: rama detect machine-learning computer-vision
Classifier: Programming Language :: Python :: 3.11
Classifier: License :: OSI Approved :: MIT License
Classifier: Operating System :: OS Independent
Requires-Python: >=3.6
Requires-Dist: absl-py ==2.0.0
Requires-Dist: astunparse ==1.6.3
Requires-Dist: backports.tarfile ==1.0.0
Requires-Dist: cachetools ==5.3.2
Requires-Dist: certifi ==2023.11.17
Requires-Dist: charset-normalizer ==3.3.2
Requires-Dist: colorama ==0.4.6
Requires-Dist: contourpy ==1.2.0
Requires-Dist: cycler ==0.12.1
Requires-Dist: docutils ==0.21.1
Requires-Dist: easyocr ==1.7.1
Requires-Dist: filelock ==3.13.1
Requires-Dist: flatbuffers ==23.5.26
Requires-Dist: fonttools ==4.46.0
Requires-Dist: fsspec ==2023.12.2
Requires-Dist: gast ==0.5.4
Requires-Dist: gitdb ==4.0.11
Requires-Dist: GitPython ==3.1.40
Requires-Dist: google-auth ==2.25.2
Requires-Dist: google-auth-oauthlib ==1.2.0
Requires-Dist: google-pasta ==0.2.0
Requires-Dist: grpcio ==1.60.0
Requires-Dist: h5py ==3.10.0
Requires-Dist: idna ==3.6
Requires-Dist: imageio ==2.33.1
Requires-Dist: importlib-metadata ==7.0.0
Requires-Dist: importlib-resources ==6.1.1
Requires-Dist: jaraco.classes ==3.4.0
Requires-Dist: jaraco.context ==5.3.0
Requires-Dist: jaraco.functools ==4.0.0
Requires-Dist: Jinja2 ==3.1.2
Requires-Dist: keras ==3.3.3
Requires-Dist: keyring ==25.1.0
Requires-Dist: kiwisolver ==1.4.5
Requires-Dist: lazy-loader ==0.3
Requires-Dist: libclang ==16.0.6
Requires-Dist: Markdown ==3.5.1
Requires-Dist: markdown-it-py ==3.0.0
Requires-Dist: MarkupSafe ==2.1.3
Requires-Dist: matplotlib ==3.8.2
Requires-Dist: mdurl ==0.1.2
Requires-Dist: ml-dtypes ==0.3.2
Requires-Dist: more-itertools ==10.2.0
Requires-Dist: mpmath ==1.3.0
Requires-Dist: namex ==0.0.8
Requires-Dist: networkx ==3.2.1
Requires-Dist: nh3 ==0.2.17
Requires-Dist: ninja ==1.11.1.1
Requires-Dist: numpy ==1.26.2
Requires-Dist: oauthlib ==3.2.2
Requires-Dist: opencv-python ==4.9.0.80
Requires-Dist: opencv-python-headless ==4.9.0.80
Requires-Dist: opt-einsum ==3.3.0
Requires-Dist: optree ==0.11.0
Requires-Dist: packaging ==23.2
Requires-Dist: pandas ==2.1.4
Requires-Dist: pillow ==10.3.0
Requires-Dist: pkginfo ==1.10.0
Requires-Dist: protobuf ==4.23.4
Requires-Dist: psutil ==5.9.6
Requires-Dist: py-cpuinfo ==9.0.0
Requires-Dist: pyasn1 ==0.5.1
Requires-Dist: pyasn1-modules ==0.3.0
Requires-Dist: pyclipper ==1.3.0.post5
Requires-Dist: Pygments ==2.17.2
Requires-Dist: pyparsing ==3.1.1
Requires-Dist: python-bidi ==0.4.2
Requires-Dist: python-dateutil ==2.8.2
Requires-Dist: pytz ==2023.3.post1
Requires-Dist: pywin32-ctypes ==0.2.2
Requires-Dist: PyYAML ==6.0.1
Requires-Dist: readme-renderer ==43.0
Requires-Dist: requests ==2.31.0
Requires-Dist: requests-oauthlib ==1.3.1
Requires-Dist: requests-toolbelt ==1.0.0
Requires-Dist: rfc3986 ==2.0.0
Requires-Dist: rich ==13.7.1
Requires-Dist: rsa ==4.9
Requires-Dist: scikit-image ==0.22.0
Requires-Dist: scipy ==1.11.4
Requires-Dist: seaborn ==0.13.0
Requires-Dist: shapely ==2.0.2
Requires-Dist: six ==1.16.0
Requires-Dist: smmap ==5.0.1
Requires-Dist: sympy ==1.12
Requires-Dist: tensorboard ==2.16.2
Requires-Dist: tensorboard-data-server ==0.7.2
Requires-Dist: tensorflow ==2.16.1
Requires-Dist: tensorflow-estimator ==2.15.0
Requires-Dist: tensorflow-intel ==2.16.1
Requires-Dist: tensorflow-io-gcs-filesystem ==0.31.0
Requires-Dist: termcolor ==2.4.0
Requires-Dist: thop ==0.1.1.post2209072238
Requires-Dist: tifffile ==2023.12.9
Requires-Dist: torch ==2.1.1
Requires-Dist: torchvision ==0.16.1
Requires-Dist: tqdm ==4.66.1
Requires-Dist: twine ==5.0.0
Requires-Dist: typing-extensions ==4.9.0
Requires-Dist: tzdata ==2023.3
Requires-Dist: ultralytics ==8.2.2
Requires-Dist: urllib3 ==2.1.0
Requires-Dist: Werkzeug ==3.0.1
Requires-Dist: wrapt ==1.14.1
Requires-Dist: zipp ==3.17.0
